Workbook

Sheet Varsayimlar
A1: NAVIAR Care — Pilot birim ekonomisi: varsayımlar
A3: Mavi hücreler girdi/varsayımdır — değiştirilebilir. Siyah hücreler formüldür.
A5: Kalem | B5: Değer | C5: Kaynak / not
A6: Yardımcı brüt saat ücreti (kr) | B6: 250 | C6: Varsayım — SeniorSupport besøksvenn honorarı 270 kr/saat bulundu, ama o gönüllü/honorar modeli; istihdamlı ücret farklı olabilir. TEYIT EDİLMELİ.
A7: Arbeidsgiveravgift — AGA (Oslo, Sone 1) | B7: 0.141 | C7: Arama özeti, Skatteetaten 2026 — doğrudan okunmadı, teyit edilmeli
A8: Feriepenger (yasal asgari) | B8: 0.102 | C8: Genel bilgi, Ferieloven §10 — teyit edilmeli
A9: OTP — zorunlu mesleki emeklilik (asgari) | B9: 0.02 | C9: Genel bilgi, OTP-loven, 1G-12G bandı — teyit edilmeli
A10: Yrkesskadeforsikring (zorunlu iş kazası sigortası) | B10: 0.0075 | C10: Kaba tahmin, branşa göre değişir — TEYIT EDİLMELİ, muhasebeciden kesin oran istenmeli
A11: MVA oranı | B11: 0.25 | C11: VAT Act standart oran — hizmet §5b sağlık muafiyetine girmiyor (kasıtlı tasarım), bkz. NAVIAR-CARE-IS-MODELI-KRITIK-ANALIZ.md §7
A12: Seyahat süresi, ödenen (dakika/ziyaret) | B12: 20 | C12: Varsayım — plan 'paid travel/time between visits' diyor, rakam vermiyor
A13: Koordinasyon payı (kr/saat, ziyaret başına) | B13: 60 | C13: Varsayım — koordinatör zamanı + CRM + genel gider payı
A14: Ödeme işleme oranı | B14: 0.02 | C14: Varsayım — kart/fatura işleme tipik oranı
A15: Hedef katkı marjı | B15: 0.3 | C15: Plan — 'Margin guardrail' (Task 2, Commercial Hypotheses)

Sheet Ziyaret Maliyet Modeli
A1: NAVIAR Care — Ziyaret başına maliyetlendirilmiş model (90/120/180 dk)
A2: Kaynak: Pilot Implementation Plan, Task 1 Step 3 — 'Model each visit with helper gross pay, employer costs, paid travel/time, insurance, coordination, payment processing.' Ortalanmış maliyet kullanılmaz (plan uyarısı).
A4: Ziyaret süresi (dk) | B4: Yardımcı brüt ücret (kr) | C4: + Feriepenger (kr) | D4: + AGA (kr) | E4: + OTP (kr) | F4: + Sigorta (kr) | G4: Yüklü yardımcı maliyeti (kr) | H4: + Seyahat (kr) | I4: + Koordinasyon (kr) | J4: + Ödeme işleme (kr) | K4: Toplam maliyet (kr)
A5: 90 | B5: =Varsayimlar!$B$6*(A5/60) | C5: =B5*Varsayimlar!$B$8 | D5: =(B5+C5)*Varsayimlar!$B$7 | E5: =B5*Varsayimlar!$B$9 | F5: =B5*Varsayimlar!$B$10 | G5: =SUM(B5:F5) | H5: =Varsayimlar!$B$6*(Varsayimlar!$B$12/60)*(1+Varsayimlar!$B$8+Varsayimlar!$B$7+Varsayimlar!$B$9+Varsayimlar!$B$10) | I5: =Varsayimlar!$B$13*(A5/60) | J5: 0 | K5: =SUM(G5:J5)
A6: 120 | B6: =Varsayimlar!$B$6*(A6/60) | C6: =B6*Varsayimlar!$B$8 | D6: =(B6+C6)*Varsayimlar!$B$7 | E6: =B6*Varsayimlar!$B$9 | F6: =B6*Varsayimlar!$B$10 | G6: =SUM(B6:F6) | H6: =Varsayimlar!$B$6*(Varsayimlar!$B$12/60)*(1+Varsayimlar!$B$8+Varsayimlar!$B$7+Varsayimlar!$B$9+Varsayimlar!$B$10) | I6: =Varsayimlar!$B$13*(A6/60) | J6: 0 | K6: =SUM(G6:J6)
A7: 180 | B7: =Varsayimlar!$B$6*(A7/60) | C7: =B7*Varsayimlar!$B$8 | D7: =(B7+C7)*Varsayimlar!$B$7 | E7: =B7*Varsayimlar!$B$9 | F7: =B7*Varsayimlar!$B$10 | G7: =SUM(B7:F7) | H7: =Varsayimlar!$B$6*(Varsayimlar!$B$12/60)*(1+Varsayimlar!$B$8+Varsayimlar!$B$7+Varsayimlar!$B$9+Varsayimlar!$B$10) | I7: =Varsayimlar!$B$13*(A7/60) | J7: 0 | K7: =SUM(G7:J7)
A9: Not: Ödeme işleme maliyeti fiyata bağlı olduğu için 'Fiyat Senaryoları' sayfasında hesaplanır, buraya 0 girildi — o sayfadaki toplam maliyet bu boşluğu doldurur.

Sheet Fiyat Senaryolari
A1: NAVIAR Care — Fiyat senaryoları ve katkı marjı testi
A2: Kaynak: Plan Task 2 — 'Test NOK 895–995/hour... Pause growth and change price if rolling four-week margin is below 30%.'
A4: Ziyaret süresi (dk) | B4: Müşteri fiyatı (kr/saat) | C4: Müşteri fiyatı (ziyaret, KDV dahil) | D4: MVA (kr) | E4: Net gelir (KDV hariç) | F4: Ödeme işleme (kr) | G4: Toplam maliyet (kr, Sayfa 2'den + işleme) | H4: Katkı (kr) | I4: Katkı marjı (%)
A5: 90 | B5: 895 | C5: =B5*(A5/60) | D5: =C5*(Varsayimlar!$B$11/(1+Varsayimlar!$B$11)) | E5: =C5-D5 | F5: =C5*Varsayimlar!$B$14 | G5: ='Ziyaret Maliyet Modeli'!G5+'Ziyaret Maliyet Modeli'!H5+'Ziyaret Maliyet Modeli'!I5+F5 | H5: =E5-G5 | I5: =IF(E5=0,0,H5/E5)
A6: 90 | B6: 995 | C6: =B6*(A6/60) | D6: =C6*(Varsayimlar!$B$11/(1+Varsayimlar!$B$11)) | E6: =C6-D6 | F6: =C6*Varsayimlar!$B$14 | G6: ='Ziyaret Maliyet Modeli'!G5+'Ziyaret Maliyet Modeli'!H5+'Ziyaret Maliyet Modeli'!I5+F6 | H6: =E6-G6 | I6: =IF(E6=0,0,H6/E6)
A7: 120 | B7: 895 | C7: =B7*(A7/60) | D7: =C7*(Varsayimlar!$B$11/(1+Varsayimlar!$B$11)) | E7: =C7-D7 | F7: =C7*Varsayimlar!$B$14 | G7: ='Ziyaret Maliyet Modeli'!G6+'Ziyaret Maliyet Modeli'!H6+'Ziyaret Maliyet Modeli'!I6+F7 | H7: =E7-G7 | I7: =IF(E7=0,0,H7/E7)
A8: 120 | B8: 995 | C8: =B8*(A8/60) | D8: =C8*(Varsayimlar!$B$11/(1+Varsayimlar!$B$11)) | E8: =C8-D8 | F8: =C8*Varsayimlar!$B$14 | G8: ='Ziyaret Maliyet Modeli'!G6+'Ziyaret Maliyet Modeli'!H6+'Ziyaret Maliyet Modeli'!I6+F8 | H8: =E8-G8 | I8: =IF(E8=0,0,H8/E8)
A9: 180 | B9: 895 | C9: =B9*(A9/60) | D9: =C9*(Varsayimlar!$B$11/(1+Varsayimlar!$B$11)) | E9: =C9-D9 | F9: =C9*Varsayimlar!$B$14 | G9: ='Ziyaret Maliyet Modeli'!G7+'Ziyaret Maliyet Modeli'!H7+'Ziyaret Maliyet Modeli'!I7+F9 | H9: =E9-G9 | I9: =IF(E9=0,0,H9/E9)
A10: 180 | B10: 995 | C10: =B10*(A10/60) | D10: =C10*(Varsayimlar!$B$11/(1+Varsayimlar!$B$11)) | E10: =C10-D10 | F10: =C10*Varsayimlar!$B$14 | G10: ='Ziyaret Maliyet Modeli'!G7+'Ziyaret Maliyet Modeli'!H7+'Ziyaret Maliyet Modeli'!I7+F10 | H10: =E10-G10 | I10: =IF(E10=0,0,H10/E10)
A12: Hedef katkı marjı (Varsayımlar sayfası): | B12: =Varsayimlar!$B$15
A13: Yukarıdaki 6 senaryodan hedefi geçenler: | B13: =COUNTIF(I5:I10,">="&B12)&" / 6"

Sheet Kapasite Senaryosu
A1: NAVIAR Care — Kapasite ve büyüklük senaryosu (plan tablosu, referans)
A2: Kaynak: Plan, 'Capacity and economics: planning scenario, not forecast.' Yıl-3 sütunu YÖN, taahhüt DEĞİL — plan kendi ifadesiyle böyle diyor.
A4: Ölçüt | B4: 90 gün kanıt hedefi | C4: Yıl 1 çıkış hedefi | D4: Yıl 3 yön (taahhüt değil)
A5: Aktif ödeyen aile | B5: 10-20 | C5: 55 | D5: 400
A6: Sunulan hizmet saati/hafta | B6: 30-60 | C6: 160 | D6: 1.200
A7: Tercih edilen/yedek yardımcı çifti | B7: 5-8 yardımcı | C7: 18-24 yardımcı | D7: 100+ yardımcı (yerel ekipler)
A8: Operasyon coğrafyası | B8: 4 iç Oslo bölgesi | C8: Oslo yoğunluk kümeleri | D8: Önce Oslo; yeni şehir yalnız Oslo playbook'u kararlıysa
